hecstac/__init__.py
hecstac/version.py
hecstac/common/__init__.py
hecstac/common/asset_factory.py
hecstac/common/base_io.py
hecstac/common/consts.py
hecstac/common/geometry.py
hecstac/common/logger.py
hecstac/common/path_manager.py
hecstac/common/proposed_features.py
hecstac/common/s3_utils.py
hecstac/common/schemas.py
hecstac/common/utils.py
hecstac/events/__init__.py
hecstac/events/hms_ffrd.py
hecstac/events/ras_ffrd.py
hecstac/events/ts_utils.py
hecstac/hms/__init__.py
hecstac/hms/assets.py
hecstac/hms/consts.py
hecstac/hms/data_model.py
hecstac/hms/item.py
hecstac/hms/parser.py
hecstac/hms/s3_utils.py
hecstac/hms/utils.py
hecstac/ras/__init__.py
hecstac/ras/assets.py
hecstac/ras/consts.py
hecstac/ras/errors.py
hecstac/ras/ffrd_calibration_check.py
hecstac/ras/item.py
hecstac/ras/parser.py
hecstac/ras/utils.py
hecstac-0.5.3.dist-info/licenses/LICENSE
hecstac-0.5.3.dist-info/METADATA
hecstac-0.5.3.dist-info/WHEEL
hecstac-0.5.3.dist-info/top_level.txt
hecstac-0.5.3.dist-info/RECORD
