Metadata-Version: 2.4
Name: hecstac
Version: 0.5.3
Summary: Create stac objects and metadata from HEC modeling software.
Maintainer-email: Seth Lawler <slawler@dewberry.com>, Scott Lawson <klawson@dewberry.com>, Stevenray Janke <sjanke@Dewberry.com>
Project-URL: repository, https://github.com/fema-ffrd/hecstac
Classifier: Development Status :: 4 - Beta
Classifier: Intended Audience :: Developers
Classifier: License :: OSI Approved :: MIT License
Classifier: Programming Language :: Python :: 3
Classifier: Programming Language :: Python :: 3.10
Classifier: Programming Language :: Python :: 3.11
Classifier: Programming Language :: Python :: 3.12
License-File: LICENSE
Requires-Dist: aiobotocore>=2.21.1
Requires-Dist: boto3>=1.37.1
Requires-Dist: botocore>=1.37.1
Requires-Dist: contextily>=1.6.2
Requires-Dist: dotenv>=0.9.9
Requires-Dist: fiona>=1.10.0rc1
Requires-Dist: fsspec==2025.3.1
Requires-Dist: geopandas>=1.0.1
Requires-Dist: matplotlib>=3.7.3
Requires-Dist: mypy-boto3-s3
Requires-Dist: obstore>=0.6.0
Requires-Dist: pystac>=1.13.0
Requires-Dist: rashdf>=0.10.0
Requires-Dist: rasqc>=0.0.3
Requires-Dist: requests>=2.32.3
Requires-Dist: s3fs==2025.3.1
Requires-Dist: shapely>=2.0.7
Requires-Dist: python-dotenv>=1.1.0
Provides-Extra: dev
Requires-Dist: pre-commit; extra == "dev"
Requires-Dist: ruff; extra == "dev"
Requires-Dist: pytest; extra == "dev"
Requires-Dist: pytest-cov; extra == "dev"
Requires-Dist: pytest-json-report; extra == "dev"
Provides-Extra: docs
Requires-Dist: sphinx; extra == "docs"
Requires-Dist: numpydoc; extra == "docs"
Requires-Dist: sphinx_rtd_theme; extra == "docs"
Requires-Dist: sphinx_design; extra == "docs"
Requires-Dist: pydata-sphinx-theme; extra == "docs"
Requires-Dist: sphinx-autodoc-typehints; extra == "docs"
Requires-Dist: myst-parser; extra == "docs"
Dynamic: license-file
